atc_tracker/__init__.py
atc_tracker/main.py
atc_tracker/commands/__init__.py
atc_tracker/commands/about.py
atc_tracker/commands/airport.py
atc_tracker/commands/flights.py
atc_tracker/commands/help.py
atc_tracker-0.1.0.dist-info/LICENSE
atc_tracker-0.1.0.dist-info/METADATA
atc_tracker-0.1.0.dist-info/WHEEL
atc_tracker-0.1.0.dist-info/entry_points.txt
atc_tracker-0.1.0.dist-info/top_level.txt
atc_tracker-0.1.0.dist-info/RECORD
